docplates/__init__.py
docplates/__main__.py
docplates/cmdline.py
docplates/docplates.py
docplates/exceptions.py
docplates/loaders.py
docplates/utils.py
docplates/version.py
docplates/plugins/__init__.py
docplates/plugins/backends/__init__.py
docplates/plugins/backends/latex.py
docplates/plugins/backends/weasyprint.py
docplates/plugins/filters/__init__.py
docplates/plugins/filters/commify.py
docplates/plugins/filters/parse_yaml.py
docplates/plugins/globals/__init__.py
docplates/plugins/globals/debug.py
docplates/plugins/globals/logger.py
docplates/plugins/globals/raise_global.py
docplates-1.0.3.dist-info/entry_points.txt
docplates-1.0.3.dist-info/LICENSE
docplates-1.0.3.dist-info/WHEEL
docplates-1.0.3.dist-info/METADATA
docplates-1.0.3.dist-info/RECORD
