Metadata-Version: 2.1
Name: docplates
Version: 1.0.3
Summary: Docplates is a PDF document templater which uses Jinja2 and LaTeX/WeasyPrint backends to create documents.
Keywords: documentation,templating,pdf
Author-email: Nigel Kukard <nkukard@LBSD.net>
Requires-Python: >=3.8
Classifier: Development Status :: 5 - Production/Stable
Classifier: Intended Audience :: Developers
Classifier: License :: OSI Approved :: GNU General Public License v3 or later (GPLv3+)
Classifier: Operating System :: POSIX :: Linux
Classifier: Programming Language :: Python :: 3 :: Only
Classifier: Topic :: Documentation
Requires-Dist: ezplugins
Requires-Dist: jinja2
Requires-Dist: pikepdf
Requires-Dist: PyYAML
Requires-Dist: setuptools
Requires-Dist: pydyf ; extra == "full"
Requires-Dist: weasyprint ; extra == "full"
Requires-Dist: pydyf ; extra == "html"
Requires-Dist: weasyprint ; extra == "html"
Project-URL: Documentation, https://software.pages.oscdev.io/docplates/docplates
Project-URL: Homepage, https://gitlab.oscdev.io/software/docplates/docplates
Project-URL: Issue Tracker, https://gitlab.oscdev.io/software/docplates/docplates/-/issues
Project-URL: Source Code, https://gitlab.oscdev.io/software/docplates/docplates
Provides-Extra: full
Provides-Extra: html
